ckanext/__init__.py
ckanext/multiuploader/__init__.py
ckanext/multiuploader/controllers.py
ckanext/multiuploader/lib.py
ckanext/multiuploader/plugin.py
ckanext/multiuploader/views.py
ckanext/multiuploader/tests/__init__.py
ckanext/multiuploader/tests/test_multiuploader.py
ckanext_multiuploader_addon-1.2.6.dist-info/licenses/LICENSE
ckanext_multiuploader_addon-1.2.6.dist-info/METADATA
ckanext_multiuploader_addon-1.2.6.dist-info/WHEEL
ckanext_multiuploader_addon-1.2.6.dist-info/entry_points.txt
ckanext_multiuploader_addon-1.2.6.dist-info/top_level.txt
ckanext_multiuploader_addon-1.2.6.dist-info/RECORD
