Metadata-Version: 2.4
Name: ckanext-multiuploader-addon
Version: 1.2.6
Summary: This CKAN extension helps users to upload multiple resources at once with drag&drop.
Home-page: https://github.com/Mat-O-Lab/ckanext-multiuploader
Author: Thomas Hanke
Author-email: thomas.hanke@iwm.fraunhofer.de
License: AGPL
Keywords: CKAN Upload
Classifier: Development Status :: 3 - Alpha
Classifier: License :: OSI Approved :: GNU Affero General Public License v3 or later (AGPLv3+)
Classifier: Programming Language :: Python :: 3
License-File: LICENSE
Dynamic: author
Dynamic: author-email
Dynamic: classifier
Dynamic: description
Dynamic: description-content-type
Dynamic: home-page
Dynamic: keywords
Dynamic: license
Dynamic: license-file
Dynamic: summary
